_kzhutil.cp35-win_amd64.pyd
kzhutil-0.0.4.dist-info/LICENSE
kzhutil-0.0.4.dist-info/METADATA
kzhutil-0.0.4.dist-info/WHEEL
kzhutil-0.0.4.dist-info/top_level.txt
kzhutil-0.0.4.dist-info/RECORD
