Metadata-Version: 2.1
Name: kzhutil
Version: 0.0.4
Summary: some python utils
Home-page: https://github.com/kuangkzh/kzhutil
Author: kuangzh
Author-email: kuangzh@smail.nju.edu.cn
License: UNKNOWN
Platform: UNKNOWN
